sem3/DDCO_lab/week3/FullAdder/design.v
module fulladd(a,b,c,sum,cout);
  input a,b,c;
  output sum,cout;
  wire [4:0]w;
  xor S1(w[0],a,b);
  xor S2(sum,w[0],c);
  and C1(w[1],a,c);
  and C2(w[2],a,b);
  and C3(w[3],b,c);
  or C4(w[4],w[1],w[2]);
  or C5(cout,w[3],w[4]);
endmodule

sem3/DDCO_lab/week3/Ripple_Carry_Adder/design.v
module Ripple(input wire [3:0] a,input wire [3:0] b, input wire cin,output wire [3:0]sum,output wire cout);
  wire [2:0] c;
  fulladd U0(a[0],b[0],cin,sum[0],c[0]);
  fulladd U1(a[1],b[1],c[0],sum[1],c[1]);
  fulladd U2(a[2],b[2],c[1],sum[2],c[2]);
  fulladd U3(a[3],b[3],c[2],sum[3],cout);
endmodule

sem3/DDCO_lab/week3/Ripple_Carry_Adder/testbech.v
`timescale 1 ns / 100 ps
`define TESTVECS 10
module tb;  
 reg clk, reset; 
 reg [3:0] i0, i1;
 reg cin;  
 wire [3:0] o; 
 wire cout; 
 reg [8:0] test_vecs [0:(`TESTVECS-1)];  
 integer i;

 initial begin 
  $dumpfile("rca_test.vcd"); 
  $dumpvars(0,tb);  
 end 

 initial begin
  reset = 1'b1; #12.5 reset = 1'b0;
 end  

 initial clk = 1'b0;
 always #5 clk =~ clk;

 initial begin   
  test_vecs[0] = 9'b000000000;   
  test_vecs[1] = 9'b000000001; 
  test_vecs[2] = 9'b000100010;  
  test_vecs[3] = 9'b000100011;    
  test_vecs[4] = 9'b001000100;  
  test_vecs[5] = 9'b001000101;  
  test_vecs[6] = 9'b101010110; 
  test_vecs[7] = 9'b101010111;
  test_vecs[8] = 9'b111011110;
  test_vecs[9] = 9'b111011111;
 end 

 initial {i0, i1, cin, i} = 0; 
 Ripple u0(i0, i1, cin, o, cout);

initial begin    #6 

for(i=0;i<`TESTVECS;i=i+1)   
   begin #10 {i0, i1, cin}=test_vecs[i]; 

 end    #100 $finish;  end
always@(i0 or i1 or cin)
$monitor("At time = %t, i0=%b, i1=%b,cin=%b,Sum = %b,Carry %b", $time,i0,i1,cin,o,cout);
endmodule

sem3/DDCO_lab/week3/Ripple_Carry_Adder/rca_test.vcd
$date
	Tue Aug 19 11:12:28 2025
$end
$version
	Icarus Verilog
$end
$timescale
	100ps
$end
$scope module tb $end
$var wire 4 ! o [3:0] $end
$var wire 1 " cout $end
$var reg 1 # cin $end
$var reg 1 $ clk $end
$var reg 4 % i0 [3:0] $end
$var reg 4 & i1 [3:0] $end
$var reg 1 ' reset $end
$var integer 32 ( i [31:0] $end
$scope module u0 $end
$var wire 4 ) a [3:0] $end
$var wire 4 * b [3:0] $end
$var wire 1 # cin $end
$var wire 4 + sum [3:0] $end
$var wire 1 " cout $end
$var wire 3 , c [2:0] $end
$scope module U0 $end
$var wire 1 - a $end
$var wire 1 . b $end
$var wire 1 # c $end
$var wire 1 / cout $end
$var wire 1 0 sum $end
$var wire 5 1 w [4:0] $end
$upscope $end
$scope module U1 $end
$var wire 1 2 a $end
$var wire 1 3 b $end
$var wire 1 4 c $end
$var wire 1 5 cout $end
$var wire 1 6 sum $end
$var wire 5 7 w [4:0] $end
$upscope $end
$scope module U2 $end
$var wire 1 8 a $end
$var wire 1 9 b $end
$var wire 1 : c $end
$var wire 1 ; cout $end
$var wire 1 < sum $end
$var wire 5 = w [4:0] $end
$upscope $end
$scope module U3 $end
$var wire 1 > a $end
$var wire 1 ? b $end
$var wire 1 @ c $end
$var wire 1 " cout $end
$var wire 1 A sum $end
$var wire 5 B w [4:0] $end
$upscope $end
$upscope $end
$upscope $end
$enddefinitions $end
$comment Show the parameter values. $end
$dumpall
$end
#0
$dumpvars
b0 B
0A
0@
0?
0>
b0 =
0<
0;
0:
09
08
b0 7
06
05
04
03
02
b0 1
00
0/
0.
0-
b0 ,
b0 +
b0 *
b0 )
b0 (
1'
b0 &
b0 %
0$
0#
0"
b0 !
$end
#50
1$
#100
0$
#125
0'
#150
1$
#160
b1 (
#200
0$
#250
1$
#260
b1 !
b1 +
10
b10 (
1#
#300
0$
#350
1$
#360
16
14
b1 ,
1/
b10100 1
1-
1.
b10 !
b10 +
00
b11 (
b1 %
b1 )
b1 &
b1 *
0#
#400
0$
#450
1$
#460
b11 !
b11 +
10
b11110 1
b100 (
1#
#500
0$
#550
1$
#560
06
04
0/
1<
1:
b10 ,
15
b10100 7
0-
12
0.
13
b100 !
b100 +
00
b0 1
b101 (
b10 %
b10 )
b10 &
b10 *
0#
#600
0$
#650
1$
#660
b101 !
b101 +
10
b110 (
1#
#700
0$
#750
1$
#760
1"
b1 1
b10100 B
1>
1.
1?
b101 !
b101 +
10
b111 (
b1010 %
b1010 )
b1011 &
b1011 *
0#
#800
0$
#850
1$
#860
16
b11110 7
14
b11 ,
1/
b110 !
b110 +
00
b1001 1
b1000 (
1#
#900
0$
#950
1$
#960
1A
b11110 B
1@
06
b10100 7
1;
04
b110 ,
0/
b11110 =
18
19
b1101 !
b1101 +
10
b1 1
b1001 (
b1110 %
b1110 )
b1111 &
b1111 *
0#
#1000
0$
#1050
1$
#1060
16
b11110 7
14
b111 ,
1/
b1110 !
b1110 +
00
b1001 1
b1010 (
1#
