sem3/DDCO_lab/week5/SR_ff/design.v
module sr_ff (
    input wire S,       // Set
    input wire R,       // Reset
    input wire clk,     // Clock
    input wire rst,     // Asynchronous reset
    output reg Q        // Output
);

    always @(posedge clk or posedge rst) begin
        if (rst)
            Q <= 1'b0;              // Async reset to 0
        else begin
            case ({S, R})
                2'b00: Q <= Q;      // No change
                2'b01: Q <= 1'b0;   // Reset
                2'b10: Q <= 1'b1;   // Set
                2'b11: Q <= 1'bx;   // Invalid (both high)
            endcase
        end
    end

endmodule

sem3/DDCO_lab/week5/SR_ff/testbench.v
module TB_SR; 
    reg S, R, CLK, RST;
    wire Q;

    // Instantiate SR flip-flop
    sr_ff uut (.S(S), .R(R), .clk(CLK), .rst(RST), .Q(Q));

    // Clock generation: 10 time unit period
    initial begin
        CLK = 1'b0;
        forever #5 CLK = ~CLK;
    end

    // Waveform dump
    initial begin
        $dumpfile("sr_ff.vcd");
        $dumpvars(0, TB_SR);
    end

    // Monitor
    initial begin
        $monitor("Time=%0t | RST=%b | S=%b | R=%b | Q=%b", $time, RST, S, R, Q);
    end

    // Stimulus
    initial begin
        RST = 1'b1; S = 0; R = 0; #7;   // Reset asserted
        RST = 1'b0; #8;                 // Release reset

        S = 1; R = 0; #20;              // Set
        S = 0; R = 1; #20;              // Reset
        S = 0; R = 0; #20;              // Hold
        S = 1; R = 1; #20;              // Invalid state (Q=x)

        RST = 1; #10;                   // Async reset again
        RST = 0; #10;

        $finish;
    end

endmodule

sem3/DDCO_lab/week5/SR_ff/sr_ff.vcd
$date
	Mon Sep  8 15:20:27 2025
$end
$version
	Icarus Verilog
$end
$timescale
	1s
$end
$scope module TB_SR $end
$var wire 1 ! Q $end
$var reg 1 " CLK $end
$var reg 1 # R $end
$var reg 1 $ RST $end
$var reg 1 % S $end
$scope module uut $end
$var wire 1 # R $end
$var wire 1 % S $end
$var wire 1 " clk $end
$var wire 1 $ rst $end
$var reg 1 ! Q $end
$upscope $end
$upscope $end
$enddefinitions $end
$comment Show the parameter values. $end
$dumpall
$end
#0
$dumpvars
0%
1$
0#
0"
0!
$end
#5
1"
#7
0$
#10
0"
#15
1!
1"
1%
#20
0"
#25
1"
#30
0"
#35
0!
1"
1#
0%
#40
0"
#45
1"
#50
0"
#55
1"
0#
#60
0"
#65
1"
#70
0"
#75
x!
1"
1#
1%
#80
0"
#85
1"
#90
0"
#95
0!
1"
1$
#100
0"
#105
x!
1"
0$
