sem3/DDCO_lab/week5/D_ff_using_T_ff/tdesign.v
module t_ff (
    input wire T,
    input wire clk,
    input wire rst,     // async reset
    output reg Q
);

    always @(posedge clk or posedge rst) begin
        if (rst)
            Q <= 1'b0;
        else if (T)
            Q <= ~Q;   // toggle
        else
            Q <= Q;    // hold
    end

endmodule

sem3/DDCO_lab/week5/D_ff_using_T_ff/design.v
module d_using_t (
    input wire D,
    input wire clk,
    input wire rst,
    output wire Q
);
    wire T;
    wire Q_int;   // must be wire, since it's driven by t_ff

    // D to T conversion
    assign T = D ^ Q_int;

    // Internal T flip-flop instance
    t_ff U1 (.T(T), .clk(clk), .rst(rst), .Q(Q_int));

    assign Q = Q_int;   // drive output
endmodule

sem3/DDCO_lab/week5/D_ff_using_T_ff/testbench.v
module TB_D_using_T;
    reg D, CLK, RST;
    wire Q;

    // Instantiate D FF (built from T FF)
    d_using_t uut (.D(D), .clk(CLK), .rst(RST), .Q(Q));

    // Clock: 10 time unit period
    initial begin
        CLK = 0;
        forever #5 CLK = ~CLK;
    end

    // Dump VCD
    initial begin
        $dumpfile("d_using_t.vcd");
        $dumpvars(0, TB_D_using_T);
    end

    // Monitor
    initial begin
        $monitor("Time=%0t | RST=%b | D=%b | Q=%b", $time, RST, D, Q);
    end

    // Stimulus
    initial begin
        RST = 1; D = 0; #7;      // Apply reset
        RST = 0; D = 0; #10;     // Expect Q=0
        D = 1; #10;              // Expect Q=1
        D = 0; #10;              // Expect Q=0
        D = 1; #20;              // Expect Q=1
        D = 1; #10;              // Hold 1
        RST = 1; #5;             // Reset again
        RST = 0; D = 0; #10;     // Back to 0
        $finish;
    end
endmodule

sem3/DDCO_lab/week5/D_ff_using_T_ff/d_using_t.vcd
$date
	Mon Sep  8 15:29:01 2025
$end
$version
	Icarus Verilog
$end
$timescale
	1s
$end
$scope module TB_D_using_T $end
$var wire 1 ! Q $end
$var reg 1 " CLK $end
$var reg 1 # D $end
$var reg 1 $ RST $end
$scope module uut $end
$var wire 1 # D $end
$var wire 1 ! Q $end
$var wire 1 % T $end
$var wire 1 " clk $end
$var wire 1 $ rst $end
$var wire 1 & Q_int $end
$scope module U1 $end
$var wire 1 % T $end
$var wire 1 " clk $end
$var wire 1 $ rst $end
$var reg 1 & Q $end
$upscope $end
$upscope $end
$upscope $end
$enddefinitions $end
$comment Show the parameter values. $end
$dumpall
$end
#0
$dumpvars
0&
0%
1$
0#
0"
0!
$end
#5
1"
#7
0$
#10
0"
#15
1"
#17
1%
1#
#20
0"
#25
0%
1!
1&
1"
#27
1%
0#
#30
0"
#35
0%
0!
0&
1"
#37
1%
1#
#40
0"
#45
0%
1!
1&
1"
#50
0"
#55
1"
#60
0"
#65
1"
#67
1%
0!
0&
1$
#70
0"
#72
0%
0#
0$
