sem3/DDCO_lab/week2/circuit3/design.v
module simple_circuit  (A, B, C, D);
output D; 
input A, B, C;
wire w1,w2,w3;
and G1 (w1,C,B);
or G2 (w2,A,w1);
and G3 (w3,A,B);
or G4 (D,w3,w2);
endmodule

sem3/DDCO_lab/week2/circuit3/testbench.v
module tb_simple_circuit;
  wire D;
  reg A, B, C;


  simple_circuit M1(A, B, C, D);

  initial begin
    A = 1'b0; B = 1'b0; C = 1'b0; #20;
    A = 1'b0; B = 1'b0; C = 1'b1; #20;
    A = 1'b0; B = 1'b1; C = 1'b0; #20;
    A = 1'b0; B = 1'b1; C = 1'b1; #20;
    A = 1'b1; B = 1'b0; C = 1'b0; #20;
    A = 1'b1; B = 1'b0; C = 1'b1; #20;
    A = 1'b1; B = 1'b1; C = 1'b0; #20;
    A = 1'b1; B = 1'b1; C = 1'b1; #20;
  end

  initial begin
    $monitor($time, " A=%b, B=%b, C=%b, D=%b ", A, B, C, D);
  end

  initial begin
    $dumpfile("tb_simple_circuit.vcd");
    $dumpvars(1, tb_simple_circuit); 
  end
endmodule

sem3/DDCO_lab/week2/circuit3/tb_simple_circuit.vcd
$date
	Mon Aug 11 09:40:52 2025
$end
$version
	Icarus Verilog
$end
$timescale
	1s
$end
$scope module tb_simple_circuit $end
$var wire 1 ! D $end
$var reg 1 " A $end
$var reg 1 # B $end
$var reg 1 $ C $end
$upscope $end
$enddefinitions $end
#0
$dumpvars
0$
0#
0"
0!
$end
#20
1$
#40
0$
1#
#60
1!
1$
#80
0$
0#
1"
#100
1$
#120
0$
1#
#140
1$
