sem3/DDCO_lab/week3/FullAdder/design.v
module fulladd(a,b,c,sum,cout);
  input a,b,c;
  output sum,cout;
  wire [4:0]w;
  xor S1(w[0],a,b);
  xor S2(sum,w[0],c);
  and C1(w[1],a,c);
  and C2(w[2],a,b);
  and C3(w[3],b,c);
  or C4(w[4],w[1],w[2]);
  or C5(cout,w[3],w[4]);
endmodule

sem3/DDCO_lab/week3/FullAdder/testbench.v
module fulladd_tb;
  reg a,b,c;
  wire s,cout;
  fulladd A1(.a(a), .b(b), .c(c), .sum(s), .cout(cout));

  initial begin
    $dumpfile("fulladd_test.vcd");
    $dumpvars(0,fulladd_tb);
  end

   initial begin
    a = 1'b0; b = 1'b0; c = 1'b0; #5;
    a = 1'b0; b = 1'b0; c = 1'b1; #5;
    a = 1'b0; b = 1'b1; c = 1'b0; #5;
    a = 1'b0; b = 1'b1; c = 1'b1; #5;
    a = 1'b1; b = 1'b0; c = 1'b0; #5;
    a = 1'b1; b = 1'b0; c = 1'b1; #5;
    a = 1'b1; b = 1'b1; c = 1'b0; #5;
    a = 1'b1; b = 1'b1; c = 1'b1; #5;
  end 



  initial begin
    $monitor($time, "a=%b, b=%b, c=%b, sum=%b, carry=%b", a, b, c, s, cout);
  end

endmodule

sem3/DDCO_lab/week3/FullAdder/fulladd_test.vcd
$date
	Tue Aug 19 10:55:53 2025
$end
$version
	Icarus Verilog
$end
$timescale
	1s
$end
$scope module fulladd_tb $end
$var wire 1 ! s $end
$var wire 1 " cout $end
$var reg 1 # a $end
$var reg 1 $ b $end
$var reg 1 % c $end
$scope module A1 $end
$var wire 1 # a $end
$var wire 1 $ b $end
$var wire 1 % c $end
$var wire 1 " cout $end
$var wire 1 ! sum $end
$var wire 5 & w [4:0] $end
$upscope $end
$upscope $end
$enddefinitions $end
$comment Show the parameter values. $end
$dumpall
$end
#0
$dumpvars
b0 &
0%
0$
0#
0"
0!
$end
#5
1!
1%
#10
1!
b1 &
0%
1$
#15
1"
0!
b1001 &
1%
#20
0"
1!
b1 &
0%
0$
1#
#25
1"
0!
b10011 &
1%
#30
0!
b10100 &
0%
1$
#35
1!
b11110 &
1%
