sem3/DDCO_lab/week6/ripple_up_counter_dff/design.v
module dff (
  input wire clk,
  input wire rst, // async reset, active-high
  input wire d,
  output reg q
);
  always @(posedge clk or posedge rst) begin
    if (rst) 
      q <= 1'b0;
    else 
      q <= d;
  end
endmodule
module ripple_up_counter_2bit (
  input wire clk,
  input wire rst,
  output wire [1:0] q
);
  wire q0, q1;

  // LSB toggles on every clock
  dff ff0 (.clk(clk), .rst(rst), .d(~q0), .q(q0));

  // MSB toggles when Q0 goes from 1 → 0 (falling edge of Q0)
  dff ff1 (.clk(~q0), .rst(rst), .d(~q1), .q(q1));

  assign q = {q1, q0};
endmodule

sem3/DDCO_lab/week6/ripple_up_counter_dff/testbench.v
`timescale 1ns/1ps

module tb_ripple_up_counter_2bit;
  reg clk;
  reg rst;
  wire [1:0] q;

  // DUT instantiation
  ripple_up_counter_2bit dut (
    .clk(clk),
    .rst(rst),
    .q(q)
  );

  // Clock generator: 10ns period
  initial begin
    clk = 0;
    forever #5 clk = ~clk;
  end

  // Stimulus
  initial begin
    // Dump waves (for GTKWave or any viewer)
    $dumpfile("ripple_up_counter_2bit.vcd");
    $dumpvars(0, tb_ripple_up_counter_2bit);

    // Apply reset
    rst = 1;
    #10;
    rst = 0;

    // Run for a few cycles
    #100;

    // Finish simulation
    $finish;
  end

  // Monitor outputs
  initial begin
    $monitor("Time=%0t | clk=%b rst=%b | q=%b",
              $time, clk, rst, q);
  end
endmodule

sem3/DDCO_lab/week6/ripple_up_counter_dff/ripple_up_counter_2bit.vcd
$date
	Mon Sep 29 22:26:31 2025
$end
$version
	Icarus Verilog
$end
$timescale
	1ps
$end
$scope module tb_ripple_up_counter_2bit $end
$var wire 2 ! q [1:0] $end
$var reg 1 " clk $end
$var reg 1 # rst $end
$scope module dut $end
$var wire 1 " clk $end
$var wire 1 # rst $end
$var wire 1 $ q1 $end
$var wire 1 % q0 $end
$var wire 2 & q [1:0] $end
$scope module ff0 $end
$var wire 1 " clk $end
$var wire 1 ' d $end
$var wire 1 # rst $end
$var reg 1 % q $end
$upscope $end
$scope module ff1 $end
$var wire 1 ( clk $end
$var wire 1 ) d $end
$var wire 1 # rst $end
$var reg 1 $ q $end
$upscope $end
$upscope $end
$upscope $end
$enddefinitions $end
$comment Show the parameter values. $end
$dumpall
$end
#0
$dumpvars
1)
1(
1'
b0 &
0%
0$
1#
0"
b0 !
$end
#5000
1"
#10000
0"
0#
#15000
0(
0'
b1 !
b1 &
1%
1"
#20000
0"
#25000
0)
1$
1(
1'
b10 !
b10 &
0%
1"
#30000
0"
#35000
0(
0'
b11 !
b11 &
1%
1"
#40000
0"
#45000
1)
0$
1(
1'
b0 !
b0 &
0%
1"
#50000
0"
#55000
0(
0'
b1 !
b1 &
1%
1"
#60000
0"
#65000
0)
1$
1(
1'
b10 !
b10 &
0%
1"
#70000
0"
#75000
0(
0'
b11 !
b11 &
1%
1"
#80000
0"
#85000
1)
0$
1(
1'
b0 !
b0 &
0%
1"
#90000
0"
#95000
0(
0'
b1 !
b1 &
1%
1"
#100000
0"
#105000
0)
1$
1(
1'
b10 !
b10 &
0%
1"
