sem3/DDCO/programs/1/design.v
/*Smart Light with Occupancy + Ambient

Inputs: L (ambient light low), P (person present), O (override ON)

Output: X (light ON)

Spec: X = 1 if (L=1 AND P=1) OR O=1.

Constraint: Implement using only NAND gates.
*/
module nand_gate (A,B,C);
  input A,B;
  output C;
  assign C = !(A&B);
endmodule

module nand_implement(L,P,O,X);
  input L,P,O;
  output X;
  wire w1,w2;
  nand_gate F1(L,P,w1);
  nand_gate F2(O,O,w2);
  nand_gate F3(w1,w2,X);
endmodule

sem3/DDCO/programs/1/testbech.v
module test_bench;
  wire X;
  reg L,P,O;

  nand_implement F(L,P,O,X);

  initial begin
    L = 1'b0; P = 1'b0; O = 1'b0; #20;
    L = 1'b0; P = 1'b0; O = 1'b1; #20;
    L = 1'b0; P = 1'b1; O = 1'b0; #20;
    L = 1'b0; P = 1'b1; O = 1'b1; #20;
    L = 1'b1; P = 1'b0; O = 1'b0; #20;
    L = 1'b1; P = 1'b0; O = 1'b1; #20;
    L = 1'b1; P = 1'b1; O = 1'b0; #20;
    L = 1'b1; P = 1'b1; O = 1'b1; #20;
  end

  initial begin
    $monitor($time, "L=%b, P=%b, O=%b, X=%b",L,P,O,X);
  end

  initial begin
    $dumpfile("dumpfile.vcd");
    $dumpvars(1,test_bench);
  end

endmodule

sem3/DDCO/programs/1/dumpfile.vcd
$date
	Sat Aug 16 10:51:46 2025
$end
$version
	Icarus Verilog
$end
$timescale
	1s
$end
$scope module test_bench $end
$var wire 1 ! X $end
$var reg 1 " L $end
$var reg 1 # O $end
$var reg 1 $ P $end
$upscope $end
$enddefinitions $end
$comment Show the parameter values. $end
$dumpall
$end
#0
$dumpvars
0$
0#
0"
0!
$end
#20
1!
1#
#40
0!
0#
1$
#60
1!
1#
#80
0!
0#
0$
1"
#100
1!
1#
#120
0#
1$
#140
1#
