sem3/DDCO_lab/week4/two_to_1_Mux/design.v
module mux2 (input wire i0, i1, j, output wire o);

  assign o = j?i0:i1;

endmodule

sem3/DDCO_lab/week4/two_to_1_Mux/testbench.v
module TB;
  reg A,B,S;
  wire X;
  initial begin
    $dumpfile("MUX2_test.vcd");
    $dumpvars(0,TB);
  end
  mux2 newMUX(.i0(A), .i1(B), .j(S), .o(X));

  initial begin
    S = 1'b0;    A = 1'b0;B = 1'b0;
    #5 S = 1'b0;A = 1'b0;B = 1'b1;
    #5 S = 1'b0;A = 1'b1;B = 1'b0;
    #5 S = 1'b0;A = 1'b1;B = 1'b1;
    #5 S = 1'b1;A = 1'b0;B = 1'b0;
    #5 S = 1'b1;A = 1'b0;B = 1'b1;
    #5 S = 1'b1;A = 1'b1;B = 1'b0;
    #5 S=1'b1;A = 1'b1;B = 1'b1;
  end
  initial begin
    $monitor($time, " A=%b, B=%b, S=%b, X=%b", A, B, S, X);
  end
endmodule

sem3/DDCO_lab/week4/two_to_1_Mux/MUX2_test.vcd
$date
	Mon Aug 25 14:22:21 2025
$end
$version
	Icarus Verilog
$end
$timescale
	1s
$end
$scope module TB $end
$var wire 1 ! X $end
$var reg 1 " A $end
$var reg 1 # B $end
$var reg 1 $ S $end
$scope module newMUX $end
$var wire 1 " i0 $end
$var wire 1 # i1 $end
$var wire 1 $ j $end
$var wire 1 ! o $end
$upscope $end
$upscope $end
$enddefinitions $end
$comment Show the parameter values. $end
$dumpall
$end
#0
$dumpvars
0$
0#
0"
0!
$end
#5
1!
1#
#10
0!
0#
1"
#15
1!
1#
#20
0!
0#
0"
1$
#25
1#
#30
1!
0#
1"
#35
1#
