sem3/DDCO_lab/week6/Up_Synchronous_counter_jkff/design.v
module jk_ff (input wire j, input wire k,input wire clk,  input wire rst,output reg q );
 always @(posedge clk or posedge rst) 
 begin       
  if (rst)     q <= 1'b0;                // Reset to 0       
  else begin
   case ({j, k})             
    2'b00: q <= q;        // No change       
    2'b01: q <= 1'b0;     // Reset       
    2'b10: q <= 1'b1;     // Set            
    2'b11: q <= ~q;       // Toggle          
   endcase
  end
 end 
endmodule

module up_counter(input clk, input reset, output[1:0]q);
  wire j0, k0, j1, k1;
  assign j0 = 1'b1;
  assign k0 = 1'b1;
  assign j1 = q[0];
  assign k1 = q[0];

  jk_ff A1(.j(j0), .k(k0), .clk(clk), .rst(reset), .q(q[0]) );
  jk_ff A2(.j(j1), .k(k1), .clk(clk), .rst(reset), .q(q[1]) );

endmodule

sem3/DDCO_lab/week6/Up_Synchronous_counter_jkff/testbench.v
module tb_up_counter_2bit;
  reg clk, reset;
  wire [1:0] q;

  up_counter uut(.clk(clk),.reset(reset), .q(q));

  //Clock generation
  initial clk = 0;
  always #5 clk = ~clk;

  //Clock period = 10;
  
  initial begin
    $dumpfile("up_counter_jk.vcd");
    $dumpvars(0, tb_up_counter_2bit);

    $display("Time\tClk\tReset\tQ1Q0");
    $monitor("%0t\t%b\t%b\t%b%b", $time, clk, reset,q[1], q[0]);
    reset = 1; #10; // Apply reset
    reset = 0; 
    #60; // Run counter for a while
    reset = 1; #10; // Reset again
    reset = 0;
    #40;
    $finish;
  end
endmodule

sem3/DDCO_lab/week6/Up_Synchronous_counter_jkff/up_counter_jk.vcd
$date
	Mon Sep 29 22:19:04 2025
$end
$version
	Icarus Verilog
$end
$timescale
	1s
$end
$scope module tb_up_counter_2bit $end
$var wire 2 ! q [1:0] $end
$var reg 1 " clk $end
$var reg 1 # reset $end
$scope module uut $end
$var wire 1 " clk $end
$var wire 1 $ j0 $end
$var wire 1 % k0 $end
$var wire 1 # reset $end
$var wire 2 & q [1:0] $end
$var wire 1 ' k1 $end
$var wire 1 ( j1 $end
$scope module A1 $end
$var wire 1 " clk $end
$var wire 1 $ j $end
$var wire 1 % k $end
$var wire 1 # rst $end
$var reg 1 ) q $end
$upscope $end
$scope module A2 $end
$var wire 1 " clk $end
$var wire 1 ( j $end
$var wire 1 ' k $end
$var wire 1 # rst $end
$var reg 1 * q $end
$upscope $end
$upscope $end
$upscope $end
$enddefinitions $end
$comment Show the parameter values. $end
$dumpall
$end
#0
$dumpvars
0*
0)
0(
0'
b0 &
1%
1$
1#
0"
b0 !
$end
#5
1"
#10
0"
0#
#15
1'
1(
b1 !
b1 &
1)
1"
#20
0"
#25
0'
0(
1*
b10 !
b10 &
0)
1"
#30
0"
#35
1'
1(
b11 !
b11 &
1)
1"
#40
0"
#45
0'
0(
0*
b0 !
b0 &
0)
1"
#50
0"
#55
1'
1(
b1 !
b1 &
1)
1"
#60
0"
#65
0'
0(
1*
b10 !
b10 &
0)
1"
#70
b0 !
b0 &
0*
0"
1#
#75
1"
#80
0"
0#
#85
1'
1(
b1 !
b1 &
1)
1"
#90
0"
#95
0'
0(
1*
b10 !
b10 &
0)
1"
#100
0"
#105
1'
1(
b11 !
b11 &
1)
1"
#110
0"
#115
0'
0(
0*
b0 !
b0 &
0)
1"
