sem3/DDCO_lab/Orange/Vending_machine.v
module vending_machine_mealy (
    input clk,
    input reset,
    input [1:0] coin,
    output reg dispense,
    output [1:0] present_state_dbg,  // <-- added
    output [1:0] next_state_dbg      // <-- added
);

    // State encoding
    parameter S0  = 2'b00;
    parameter S5  = 2'b01;
    parameter S10 = 2'b10;
    parameter S15 = 2'b11;

    reg [1:0] present_state, next_state;

    // Debug assignments
    assign present_state_dbg = present_state;
    assign next_state_dbg    = next_state;

    // State register
    always @(posedge clk or posedge reset) begin
        if (reset)
            present_state <= S0;
        else
            present_state <= next_state;
    end

    // Next state logic + output (Mealy)
    always @(*) begin
        dispense = 0;
        case (present_state)
            S0: begin
                if (coin == 2'b01) next_state = S5;
                else if (coin == 2'b10) next_state = S10;
                else next_state = S0;
            end
            S5: begin
                if (coin == 2'b01) next_state = S10;
                else if (coin == 2'b10) begin
                    next_state = S15;
                    dispense = 1;
                end else next_state = S5;
            end
            S10: begin
                if (coin == 2'b01) begin
                    next_state = S15;
                    dispense = 1;
                end else if (coin == 2'b10) begin
                    next_state = S15;
                    dispense = 1;
                end else next_state = S10;
            end
            S15: begin
                next_state = S0;
                dispense = 0;
            end
            default: next_state = S0;
        endcase
    end
endmodule

sem3/DDCO_lab/Orange/testbench.v
`timescale 1ns/1ps

module tb_vending_machine;

    reg clk;
    reg reset;
    reg [1:0] coin;
    wire dispense;

    // Debug wires for state monitoring
    wire [1:0] present_state_dbg;
    wire [1:0] next_state_dbg;

    // Instantiate DUT (make sure your DUT has these debug outputs!)
    vending_machine_mealy uut (
        .clk(clk),
        .reset(reset),
        .coin(coin),
        .dispense(dispense),
        .present_state_dbg(present_state_dbg), // debug state
        .next_state_dbg(next_state_dbg)        // debug next state
    );

    // Clock generation (10 ns period)
    initial clk = 0;
    always #5 clk = ~clk;

    // Reset sequence
    initial begin
        reset = 1;
        #12 reset = 0;   // release reset after some time
    end

    // Stimulus
    initial begin
        $dumpfile("vending_machine_tb.vcd");
        $dumpvars(0, tb_vending_machine);

        // Start with no coin
        coin = 2'b00;

        // Test case 1: 5 + 10 = 15 → should dispense
        #20 coin = 2'b01;  // insert 5
        #20 coin = 2'b10;  // insert 10
        #20 coin = 2'b00;

        // Test case 2: 10 + 5 = 15 → should dispense
        #20 coin = 2'b10;  // insert 10
        #20 coin = 2'b01;  // insert 5
        #20 coin = 2'b00;

        // Test case 3: 10 + 10 = 20 → should dispense and carry 5
        #20 coin = 2'b10;  // insert 10
        #20 coin = 2'b10;  // insert 10
        #20 coin = 2'b00;

        // Test case 4: 5 + 5 + 5 = 15 → should dispense
        #20 coin = 2'b01;  // insert 5
        #20 coin = 2'b01;  // insert 5
        #20 coin = 2'b01;  // insert 5
        #20 coin = 2'b00;

        // Idle for some time
        #50 coin = 2'b00;

        $finish;
    end

    // Simple state monitor
    initial begin
        $monitor("T=%0t | Reset=%b | Coin=%b | State=%b -> Next=%b | Dispense=%b",
                 $time, reset, coin, present_state_dbg, next_state_dbg, dispense);
    end

endmodule

sem3/DDCO_lab/Orange/vending_machine_tb.vcd
$date
	Mon Sep 15 15:02:52 2025
$end
$version
	Icarus Verilog
$end
$timescale
	1ps
$end
$scope module tb_vending_machine $end
$var wire 2 ! present_state_dbg [1:0] $end
$var wire 2 " next_state_dbg [1:0] $end
$var wire 1 # dispense $end
$var reg 1 $ clk $end
$var reg 2 % coin [1:0] $end
$var reg 1 & reset $end
$scope module uut $end
$var wire 1 $ clk $end
$var wire 2 ' coin [1:0] $end
$var wire 2 ( next_state_dbg [1:0] $end
$var wire 2 ) present_state_dbg [1:0] $end
$var wire 1 & reset $end
$var parameter 2 * S0 $end
$var parameter 2 + S10 $end
$var parameter 2 , S15 $end
$var parameter 2 - S5 $end
$var reg 1 # dispense $end
$var reg 2 . next_state [1:0] $end
$var reg 2 / present_state [1:0] $end
$upscope $end
$upscope $end
$enddefinitions $end
$comment Show the parameter values. $end
$dumpall
b1 -
b11 ,
b10 +
b0 *
$end
#0
$dumpvars
b0 /
b0 .
b0 )
b0 (
b0 '
1&
b0 %
0$
0#
b0 "
b0 !
$end
#5000
1$
#10000
0$
#12000
0&
#15000
1$
#20000
b1 "
b1 (
b1 .
0$
b1 %
b1 '
#25000
b10 "
b10 (
b10 .
b1 !
b1 )
b1 /
1$
#30000
0$
#35000
1#
b11 "
b11 (
b11 .
b10 !
b10 )
b10 /
1$
#40000
1#
0$
b10 %
b10 '
#45000
b0 "
b0 (
b0 .
0#
b11 !
b11 )
b11 /
1$
#50000
0$
#55000
b10 "
b10 (
b10 .
b0 !
b0 )
b0 /
1$
#60000
b0 "
b0 (
b0 .
0$
b0 %
b0 '
#65000
1$
#70000
0$
#75000
1$
#80000
b10 "
b10 (
b10 .
0$
b10 %
b10 '
#85000
1#
b11 "
b11 (
b11 .
b10 !
b10 )
b10 /
1$
#90000
0$
#95000
b0 "
b0 (
b0 .
0#
b11 !
b11 )
b11 /
1$
#100000
0$
b1 %
b1 '
#105000
b1 "
b1 (
b1 .
b0 !
b0 )
b0 /
1$
#110000
0$
#115000
b10 "
b10 (
b10 .
b1 !
b1 )
b1 /
1$
#120000
b1 "
b1 (
b1 .
0$
b0 %
b0 '
#125000
1$
#130000
0$
#135000
1$
#140000
1#
b11 "
b11 (
b11 .
0$
b10 %
b10 '
#145000
b0 "
b0 (
b0 .
0#
b11 !
b11 )
b11 /
1$
#150000
0$
#155000
b10 "
b10 (
b10 .
b0 !
b0 )
b0 /
1$
#160000
0$
#165000
1#
b11 "
b11 (
b11 .
b10 !
b10 )
b10 /
1$
#170000
0$
#175000
b0 "
b0 (
b0 .
0#
b11 !
b11 )
b11 /
1$
#180000
0$
b0 %
b0 '
#185000
b0 !
b0 )
b0 /
1$
#190000
0$
#195000
1$
#200000
b1 "
b1 (
b1 .
0$
b1 %
b1 '
#205000
b10 "
b10 (
b10 .
b1 !
b1 )
b1 /
1$
#210000
0$
#215000
1#
b11 "
b11 (
b11 .
b10 !
b10 )
b10 /
1$
#220000
0$
#225000
b0 "
b0 (
b0 .
0#
b11 !
b11 )
b11 /
1$
#230000
0$
#235000
b1 "
b1 (
b1 .
b0 !
b0 )
b0 /
1$
#240000
0$
#245000
b10 "
b10 (
b10 .
b1 !
b1 )
b1 /
1$
#250000
0$
#255000
1#
b11 "
b11 (
b11 .
b10 !
b10 )
b10 /
1$
#260000
b10 "
b10 (
b10 .
0#
0$
b0 %
b0 '
