sem3/DDCO_lab/week2/circuit1/design.v
module simple_circuit  (A, B, C, D, E);
output D, E;  input A, B, C;  wire w1;
and G1 (w1,A,B); // Optional  gate instance name
not G2 (E,C);
or G3 ( D, w1 ,E);
endmodule

sem3/DDCO_lab/week2/circuit1/testbench.v
module tb_simple_circuit;
  wire D, E;
  reg A, B, C;

  simple_circuit M1(A, B, C, D, E);

  initial begin
    A = 1'b0; B = 1'b0; C = 1'b0; #20;
    A = 1'b0; B = 1'b0; C = 1'b1; #20;
    A = 1'b0; B = 1'b1; C = 1'b0; #20;
    A = 1'b0; B = 1'b1; C = 1'b1; #20;
    A = 1'b1; B = 1'b0; C = 1'b0; #20;
    A = 1'b1; B = 1'b0; C = 1'b1; #20;
    A = 1'b1; B = 1'b1; C = 1'b0; #20;
    A = 1'b1; B = 1'b1; C = 1'b1; #20;
  end

  initial begin
    $monitor($time, " A=%b, B=%b, C=%b, D=%b, E=%b", A, B, C, D, E);
  end

  initial begin
    $dumpfile("tb_simple_circuit.vcd");
    $dumpvars(1, tb_simple_circuit); 
  end
endmodule

sem3/DDCO_lab/week2/circuit1/tb_simple_circuit.vcd
$date
	Mon Aug 11 09:30:12 2025
$end
$version
	Icarus Verilog
$end
$timescale
	1s
$end
$scope module tb_simple_circuit $end
$var wire 1 ! D $end
$var wire 1 " E $end
$var reg 1 # A $end
$var reg 1 $ B $end
$var reg 1 % C $end
$upscope $end
$enddefinitions $end
#0
$dumpvars
0%
0$
0#
1"
1!
$end
#20
0!
0"
1%
#40
1!
1"
0%
1$
#60
0!
0"
1%
#80
1!
1"
0%
0$
1#
#100
0!
0"
1%
#120
1!
1"
0%
1$
#140
0"
1%
