sem3/DDCO_lab/week3/additional_question/design.v

  /*  Design a digital system that adds two decimal digits represented in BCD format and outputs the result in BCD. Explain the need for correction in the result and implement it in Verilog.

What should be verified in simulation?
*/
// BCD Adder
module bcd_adder(
    input  [3:0] a, b,   // two BCD digits (0–9)
    input        cin,    // carry in
    output [3:0] sum,    // BCD ones digit
    output [3:0] tens,   // BCD tens digit
    output       cout    // carry out
);

    wire [4:0] binary_sum;     // can go up to 19
    wire [4:0] corrected_sum;

    // Step 1: Normal binary addition
    assign binary_sum = a + b + cin;

    // Step 2: Apply correction if needed
    assign corrected_sum = (binary_sum > 9) ? (binary_sum + 5'd6) : binary_sum;

    // Step 3: Extract BCD digits
    assign sum  = corrected_sum[3:0]; // ones place
    assign tens = corrected_sum[4];   // tens place (only 0 or 1 possible)
    assign cout = corrected_sum[4];   // same as tens

endmodule

sem3/DDCO_lab/week3/additional_question/testbench.v
`timescale 1ns/1ps

module tb_bcd_adder;
    reg  [3:0] a, b;
    reg        cin;
    wire [3:0] sum, tens;
    wire       cout;

    // Instantiate DUT
    bcd_adder uut (
        .a(a), .b(b), .cin(cin),
        .sum(sum), .tens(tens), .cout(cout)
    );

    integer i, j, k;

    initial begin
        $dumpfile("bcd_adder_tb.vcd");   // for waveform view
        $dumpvars(0, tb_bcd_adder);

        // Loop through all valid inputs
        for (i = 0; i <= 9; i = i + 1) begin
            for (j = 0; j <= 9; j = j + 1) begin
                for (k = 0; k <= 1; k = k + 1) begin
                    a   = i;
                    b   = j;
                    cin = k;
                    #5; // wait for result

                    $display("a=%d b=%d cin=%d => tens=%d sum=%d cout=%d",
                             a, b, cin, tens, sum, cout);
                end
            end
        end

        $finish;
    end
endmodule

sem3/DDCO_lab/week3/additional_question/bcd_adder_tb.vcd
$date
	Fri Aug 22 19:56:04 2025
$end
$version
	Icarus Verilog
$end
$timescale
	1ps
$end
$scope module tb_bcd_adder $end
$var wire 4 ! tens [3:0] $end
$var wire 4 " sum [3:0] $end
$var wire 1 # cout $end
$var reg 4 $ a [3:0] $end
$var reg 4 % b [3:0] $end
$var reg 1 & cin $end
$var integer 32 ' i [31:0] $end
$var integer 32 ( j [31:0] $end
$var integer 32 ) k [31:0] $end
$scope module uut $end
$var wire 4 * a [3:0] $end
$var wire 4 + b [3:0] $end
$var wire 1 & cin $end
$var wire 4 , tens [3:0] $end
$var wire 4 - sum [3:0] $end
$var wire 1 # cout $end
$var wire 5 . corrected_sum [4:0] $end
$var wire 5 / binary_sum [4:0] $end
$upscope $end
$upscope $end
$enddefinitions $end
$comment Show the parameter values. $end
$dumpall
$end
#0
$dumpvars
b0 /
b0 .
b0 -
b0 ,
b0 +
b0 *
b0 )
b0 (
b0 '
0&
b0 %
b0 $
0#
b0 "
b0 !
$end
#5000
b1 "
b1 -
b1 .
b1 /
1&
b1 )
#10000
0&
b1 /
b1 %
b1 +
b1 (
b0 )
#15000
b10 "
b10 -
b10 .
b10 /
1&
b1 )
#20000
0&
b10 /
b10 %
b10 +
b10 (
b0 )
#25000
b11 "
b11 -
b11 .
b11 /
1&
b1 )
#30000
0&
b11 /
b11 %
b11 +
b11 (
b0 )
#35000
b100 "
b100 -
b100 .
b100 /
1&
b1 )
#40000
0&
b100 /
b100 %
b100 +
b100 (
b0 )
#45000
b101 "
b101 -
b101 .
b101 /
1&
b1 )
#50000
0&
b101 /
b101 %
b101 +
b101 (
b0 )
#55000
b110 "
b110 -
b110 .
b110 /
1&
b1 )
#60000
0&
b110 /
b110 %
b110 +
b110 (
b0 )
#65000
b111 "
b111 -
b111 .
b111 /
1&
b1 )
#70000
0&
b111 /
b111 %
b111 +
b111 (
b0 )
#75000
b1000 "
b1000 -
b1000 .
b1000 /
1&
b1 )
#80000
0&
b1000 /
b1000 %
b1000 +
b1000 (
b0 )
#85000
b1001 "
b1001 -
b1001 .
b1001 /
1&
b1 )
#90000
0&
b1001 /
b1001 %
b1001 +
b1001 (
b0 )
#95000
b0 "
b0 -
b1 !
b1 ,
1#
b10000 .
b1010 /
1&
b1 )
#100000
b1 "
b1 -
b0 !
b0 ,
0#
b1 .
0&
b0 %
b0 +
b1 /
b1 $
b1 *
b1 '
b0 (
b0 )
#105000
b10 "
b10 -
b10 .
b10 /
1&
b1 )
#110000
0&
b10 /
b1 %
b1 +
b1 (
b0 )
#115000
b11 "
b11 -
b11 .
b11 /
1&
b1 )
#120000
0&
b11 /
b10 %
b10 +
b10 (
b0 )
#125000
b100 "
b100 -
b100 .
b100 /
1&
b1 )
#130000
0&
b100 /
b11 %
b11 +
b11 (
b0 )
#135000
b101 "
b101 -
b101 .
b101 /
1&
b1 )
#140000
0&
b101 /
b100 %
b100 +
b100 (
b0 )
#145000
b110 "
b110 -
b110 .
b110 /
1&
b1 )
#150000
0&
b110 /
b101 %
b101 +
b101 (
b0 )
#155000
b111 "
b111 -
b111 .
b111 /
1&
b1 )
#160000
0&
b111 /
b110 %
b110 +
b110 (
b0 )
#165000
b1000 "
b1000 -
b1000 .
b1000 /
1&
b1 )
#170000
0&
b1000 /
b111 %
b111 +
b111 (
b0 )
#175000
b1001 "
b1001 -
b1001 .
b1001 /
1&
b1 )
#180000
0&
b1001 /
b1000 %
b1000 +
b1000 (
b0 )
#185000
b0 "
b0 -
b1 !
b1 ,
1#
b10000 .
b1010 /
1&
b1 )
#190000
0&
b1010 /
b1001 %
b1001 +
b1001 (
b0 )
#195000
b1 "
b1 -
b10001 .
b1011 /
1&
b1 )
#200000
b10 "
b10 -
b0 !
b0 ,
0#
b10 .
0&
b0 %
b0 +
b10 /
b10 $
b10 *
b10 '
b0 (
b0 )
#205000
b11 "
b11 -
b11 .
b11 /
1&
b1 )
#210000
0&
b11 /
b1 %
b1 +
b1 (
b0 )
#215000
b100 "
b100 -
b100 .
b100 /
1&
b1 )
#220000
0&
b100 /
b10 %
b10 +
b10 (
b0 )
#225000
b101 "
b101 -
b101 .
b101 /
1&
b1 )
#230000
0&
b101 /
b11 %
b11 +
b11 (
b0 )
#235000
b110 "
b110 -
b110 .
b110 /
1&
b1 )
#240000
0&
b110 /
b100 %
b100 +
b100 (
b0 )
#245000
b111 "
b111 -
b111 .
b111 /
1&
b1 )
#250000
0&
b111 /
b101 %
b101 +
b101 (
b0 )
#255000
b1000 "
b1000 -
b1000 .
b1000 /
1&
b1 )
#260000
0&
b1000 /
b110 %
b110 +
b110 (
b0 )
#265000
b1001 "
b1001 -
b1001 .
b1001 /
1&
b1 )
#270000
0&
b1001 /
b111 %
b111 +
b111 (
b0 )
#275000
b0 "
b0 -
b1 !
b1 ,
1#
b10000 .
b1010 /
1&
b1 )
#280000
0&
b1010 /
b1000 %
b1000 +
b1000 (
b0 )
#285000
b1 "
b1 -
b10001 .
b1011 /
1&
b1 )
#290000
0&
b1011 /
b1001 %
b1001 +
b1001 (
b0 )
#295000
b10 "
b10 -
b10010 .
b1100 /
1&
b1 )
#300000
b11 "
b11 -
b0 !
b0 ,
0#
b11 .
0&
b0 %
b0 +
b11 /
b11 $
b11 *
b11 '
b0 (
b0 )
#305000
b100 "
b100 -
b100 .
b100 /
1&
b1 )
#310000
0&
b100 /
b1 %
b1 +
b1 (
b0 )
#315000
b101 "
b101 -
b101 .
b101 /
1&
b1 )
#320000
0&
b101 /
b10 %
b10 +
b10 (
b0 )
#325000
b110 "
b110 -
b110 .
b110 /
1&
b1 )
#330000
0&
b110 /
b11 %
b11 +
b11 (
b0 )
#335000
b111 "
b111 -
b111 .
b111 /
1&
b1 )
#340000
0&
b111 /
b100 %
b100 +
b100 (
b0 )
#345000
b1000 "
b1000 -
b1000 .
b1000 /
1&
b1 )
#350000
0&
b1000 /
b101 %
b101 +
b101 (
b0 )
#355000
b1001 "
b1001 -
b1001 .
b1001 /
1&
b1 )
#360000
0&
b1001 /
b110 %
b110 +
b110 (
b0 )
#365000
b0 "
b0 -
b1 !
b1 ,
1#
b10000 .
b1010 /
1&
b1 )
#370000
0&
b1010 /
b111 %
b111 +
b111 (
b0 )
#375000
b1 "
b1 -
b10001 .
b1011 /
1&
b1 )
#380000
0&
b1011 /
b1000 %
b1000 +
b1000 (
b0 )
#385000
b10 "
b10 -
b10010 .
b1100 /
1&
b1 )
#390000
0&
b1100 /
b1001 %
b1001 +
b1001 (
b0 )
#395000
b11 "
b11 -
b10011 .
b1101 /
1&
b1 )
#400000
b100 "
b100 -
b0 !
b0 ,
0#
b100 .
0&
b0 %
b0 +
b100 /
b100 $
b100 *
b100 '
b0 (
b0 )
#405000
b101 "
b101 -
b101 .
b101 /
1&
b1 )
#410000
0&
b101 /
b1 %
b1 +
b1 (
b0 )
#415000
b110 "
b110 -
b110 .
b110 /
1&
b1 )
#420000
0&
b110 /
b10 %
b10 +
b10 (
b0 )
#425000
b111 "
b111 -
b111 .
b111 /
1&
b1 )
#430000
0&
b111 /
b11 %
b11 +
b11 (
b0 )
#435000
b1000 "
b1000 -
b1000 .
b1000 /
1&
b1 )
#440000
0&
b1000 /
b100 %
b100 +
b100 (
b0 )
#445000
b1001 "
b1001 -
b1001 .
b1001 /
1&
b1 )
#450000
0&
b1001 /
b101 %
b101 +
b101 (
b0 )
#455000
b0 "
b0 -
b1 !
b1 ,
1#
b10000 .
b1010 /
1&
b1 )
#460000
0&
b1010 /
b110 %
b110 +
b110 (
b0 )
#465000
b1 "
b1 -
b10001 .
b1011 /
1&
b1 )
#470000
0&
b1011 /
b111 %
b111 +
b111 (
b0 )
#475000
b10 "
b10 -
b10010 .
b1100 /
1&
b1 )
#480000
0&
b1100 /
b1000 %
b1000 +
b1000 (
b0 )
#485000
b11 "
b11 -
b10011 .
b1101 /
1&
b1 )
#490000
0&
b1101 /
b1001 %
b1001 +
b1001 (
b0 )
#495000
b100 "
b100 -
b10100 .
b1110 /
1&
b1 )
#500000
b101 "
b101 -
b0 !
b0 ,
0#
b101 .
0&
b0 %
b0 +
b101 /
b101 $
b101 *
b101 '
b0 (
b0 )
#505000
b110 "
b110 -
b110 .
b110 /
1&
b1 )
#510000
0&
b110 /
b1 %
b1 +
b1 (
b0 )
#515000
b111 "
b111 -
b111 .
b111 /
1&
b1 )
#520000
0&
b111 /
b10 %
b10 +
b10 (
b0 )
#525000
b1000 "
b1000 -
b1000 .
b1000 /
1&
b1 )
#530000
0&
b1000 /
b11 %
b11 +
b11 (
b0 )
#535000
b1001 "
b1001 -
b1001 .
b1001 /
1&
b1 )
#540000
0&
b1001 /
b100 %
b100 +
b100 (
b0 )
#545000
b0 "
b0 -
b1 !
b1 ,
1#
b10000 .
b1010 /
1&
b1 )
#550000
0&
b1010 /
b101 %
b101 +
b101 (
b0 )
#555000
b1 "
b1 -
b10001 .
b1011 /
1&
b1 )
#560000
0&
b1011 /
b110 %
b110 +
b110 (
b0 )
#565000
b10 "
b10 -
b10010 .
b1100 /
1&
b1 )
#570000
0&
b1100 /
b111 %
b111 +
b111 (
b0 )
#575000
b11 "
b11 -
b10011 .
b1101 /
1&
b1 )
#580000
0&
b1101 /
b1000 %
b1000 +
b1000 (
b0 )
#585000
b100 "
b100 -
b10100 .
b1110 /
1&
b1 )
#590000
0&
b1110 /
b1001 %
b1001 +
b1001 (
b0 )
#595000
b101 "
b101 -
b10101 .
b1111 /
1&
b1 )
#600000
b110 "
b110 -
b0 !
b0 ,
0#
b110 .
0&
b0 %
b0 +
b110 /
b110 $
b110 *
b110 '
b0 (
b0 )
#605000
b111 "
b111 -
b111 .
b111 /
1&
b1 )
#610000
0&
b111 /
b1 %
b1 +
b1 (
b0 )
#615000
b1000 "
b1000 -
b1000 .
b1000 /
1&
b1 )
#620000
0&
b1000 /
b10 %
b10 +
b10 (
b0 )
#625000
b1001 "
b1001 -
b1001 .
b1001 /
1&
b1 )
#630000
0&
b1001 /
b11 %
b11 +
b11 (
b0 )
#635000
b0 "
b0 -
b1 !
b1 ,
1#
b10000 .
b1010 /
1&
b1 )
#640000
0&
b1010 /
b100 %
b100 +
b100 (
b0 )
#645000
b1 "
b1 -
b10001 .
b1011 /
1&
b1 )
#650000
0&
b1011 /
b101 %
b101 +
b101 (
b0 )
#655000
b10 "
b10 -
b10010 .
b1100 /
1&
b1 )
#660000
0&
b1100 /
b110 %
b110 +
b110 (
b0 )
#665000
b11 "
b11 -
b10011 .
b1101 /
1&
b1 )
#670000
0&
b1101 /
b111 %
b111 +
b111 (
b0 )
#675000
b100 "
b100 -
b10100 .
b1110 /
1&
b1 )
#680000
0&
b1110 /
b1000 %
b1000 +
b1000 (
b0 )
#685000
b101 "
b101 -
b10101 .
b1111 /
1&
b1 )
#690000
0&
b1111 /
b1001 %
b1001 +
b1001 (
b0 )
#695000
b110 "
b110 -
b10110 .
b10000 /
1&
b1 )
#700000
b111 "
b111 -
b0 !
b0 ,
0#
b111 .
0&
b0 %
b0 +
b111 /
b111 $
b111 *
b111 '
b0 (
b0 )
#705000
b1000 "
b1000 -
b1000 .
b1000 /
1&
b1 )
#710000
0&
b1000 /
b1 %
b1 +
b1 (
b0 )
#715000
b1001 "
b1001 -
b1001 .
b1001 /
1&
b1 )
#720000
0&
b1001 /
b10 %
b10 +
b10 (
b0 )
#725000
b0 "
b0 -
b1 !
b1 ,
1#
b10000 .
b1010 /
1&
b1 )
#730000
0&
b1010 /
b11 %
b11 +
b11 (
b0 )
#735000
b1 "
b1 -
b10001 .
b1011 /
1&
b1 )
#740000
0&
b1011 /
b100 %
b100 +
b100 (
b0 )
#745000
b10 "
b10 -
b10010 .
b1100 /
1&
b1 )
#750000
0&
b1100 /
b101 %
b101 +
b101 (
b0 )
#755000
b11 "
b11 -
b10011 .
b1101 /
1&
b1 )
#760000
0&
b1101 /
b110 %
b110 +
b110 (
b0 )
#765000
b100 "
b100 -
b10100 .
b1110 /
1&
b1 )
#770000
0&
b1110 /
b111 %
b111 +
b111 (
b0 )
#775000
b101 "
b101 -
b10101 .
b1111 /
1&
b1 )
#780000
0&
b1111 /
b1000 %
b1000 +
b1000 (
b0 )
#785000
b110 "
b110 -
b10110 .
b10000 /
1&
b1 )
#790000
0&
b10000 /
b1001 %
b1001 +
b1001 (
b0 )
#795000
b111 "
b111 -
b10111 .
b10001 /
1&
b1 )
#800000
b1000 "
b1000 -
b0 !
b0 ,
0#
b1000 .
0&
b0 %
b0 +
b1000 /
b1000 $
b1000 *
b1000 '
b0 (
b0 )
#805000
b1001 "
b1001 -
b1001 .
b1001 /
1&
b1 )
#810000
0&
b1001 /
b1 %
b1 +
b1 (
b0 )
#815000
b0 "
b0 -
b1 !
b1 ,
1#
b10000 .
b1010 /
1&
b1 )
#820000
0&
b1010 /
b10 %
b10 +
b10 (
b0 )
#825000
b1 "
b1 -
b10001 .
b1011 /
1&
b1 )
#830000
0&
b1011 /
b11 %
b11 +
b11 (
b0 )
#835000
b10 "
b10 -
b10010 .
b1100 /
1&
b1 )
#840000
0&
b1100 /
b100 %
b100 +
b100 (
b0 )
#845000
b11 "
b11 -
b10011 .
b1101 /
1&
b1 )
#850000
0&
b1101 /
b101 %
b101 +
b101 (
b0 )
#855000
b100 "
b100 -
b10100 .
b1110 /
1&
b1 )
#860000
0&
b1110 /
b110 %
b110 +
b110 (
b0 )
#865000
b101 "
b101 -
b10101 .
b1111 /
1&
b1 )
#870000
0&
b1111 /
b111 %
b111 +
b111 (
b0 )
#875000
b110 "
b110 -
b10110 .
b10000 /
1&
b1 )
#880000
0&
b10000 /
b1000 %
b1000 +
b1000 (
b0 )
#885000
b111 "
b111 -
b10111 .
b10001 /
1&
b1 )
#890000
0&
b10001 /
b1001 %
b1001 +
b1001 (
b0 )
#895000
b1000 "
b1000 -
b11000 .
b10010 /
1&
b1 )
#900000
b1001 "
b1001 -
b0 !
b0 ,
0#
b1001 .
0&
b0 %
b0 +
b1001 /
b1001 $
b1001 *
b1001 '
b0 (
b0 )
#905000
b0 "
b0 -
b1 !
b1 ,
1#
b10000 .
b1010 /
1&
b1 )
#910000
0&
b1010 /
b1 %
b1 +
b1 (
b0 )
#915000
b1 "
b1 -
b10001 .
b1011 /
1&
b1 )
#920000
0&
b1011 /
b10 %
b10 +
b10 (
b0 )
#925000
b10 "
b10 -
b10010 .
b1100 /
1&
b1 )
#930000
0&
b1100 /
b11 %
b11 +
b11 (
b0 )
#935000
b11 "
b11 -
b10011 .
b1101 /
1&
b1 )
#940000
0&
b1101 /
b100 %
b100 +
b100 (
b0 )
#945000
b100 "
b100 -
b10100 .
b1110 /
1&
b1 )
#950000
0&
b1110 /
b101 %
b101 +
b101 (
b0 )
#955000
b101 "
b101 -
b10101 .
b1111 /
1&
b1 )
#960000
0&
b1111 /
b110 %
b110 +
b110 (
b0 )
#965000
b110 "
b110 -
b10110 .
b10000 /
1&
b1 )
#970000
0&
b10000 /
b111 %
b111 +
b111 (
b0 )
#975000
b111 "
b111 -
b10111 .
b10001 /
1&
b1 )
#980000
0&
b10001 /
b1000 %
b1000 +
b1000 (
b0 )
#985000
b1000 "
b1000 -
b11000 .
b10010 /
1&
b1 )
#990000
0&
b10010 /
b1001 %
b1001 +
b1001 (
b0 )
#995000
b1001 "
b1001 -
b11001 .
b10011 /
1&
b1 )
#1000000
b1010 '
b1010 (
b10 )
