sem3/DDCO_lab/week2/circuit4/design.v
module simple_circuit  (A, B, O, F);
output F;
input A, B, O;  
wire w1;
and G1 (w1,A,B);
or G2 (F,w1,O);
endmodule

sem3/DDCO_lab/week2/circuit4/testbench.v
module tb_simple_circuit;
  wire F;
  reg A, B, O;

  simple_circuit M1(A, B, O, F);

  initial begin
    A = 1'b0; B = 1'b0; O = 1'b0; #20;
    A = 1'b0; B = 1'b0; O = 1'b1; #20;
    A = 1'b0; B = 1'b1; O = 1'b0; #20;
    A = 1'b0; B = 1'b1; O = 1'b1; #20;
    A = 1'b1; B = 1'b0; O = 1'b0; #20;
    A = 1'b1; B = 1'b0; O = 1'b1; #20;
    A = 1'b1; B = 1'b1; O = 1'b0; #20;
    A = 1'b1; B = 1'b1; O = 1'b1; #20;
  end

  initial begin
    $monitor($time, " A=%b, B=%b, O=%b, F=%b ", A, B, O, F);
  end

  initial begin
    $dumpfile("tb_simple_circuit.vcd");
    $dumpvars(1, tb_simple_circuit); 
  end
endmodule

sem3/DDCO_lab/week2/circuit4/tb_simple_circuit.vcd
$date
	Mon Aug 11 16:38:32 2025
$end
$version
	Icarus Verilog
$end
$timescale
	1s
$end
$scope module tb_simple_circuit $end
$var wire 1 ! F $end
$var reg 1 " A $end
$var reg 1 # B $end
$var reg 1 $ O $end
$upscope $end
$enddefinitions $end
$comment Show the parameter values. $end
$dumpall
$end
#0
$dumpvars
0$
0#
0"
0!
$end
#20
1!
1$
#40
0!
0$
1#
#60
1!
1$
#80
0!
0$
0#
1"
#100
1!
1$
#120
0$
1#
#140
1$
