sem3/DDCO_lab/week5/D_ff/design.v
module d_ff (input wire D, input wire clk, input wire rst, output reg Q);
  always @(posedge clk or posedge rst) 
    begin  
      if (rst) Q <= 1'b0;     // Asynchronous reset to 0   
      else      Q <= D;        // Sample D on rising edge of clock
    end
endmodule

sem3/DDCO_lab/week5/D_ff/testbench.v
module TB_D; 
  reg D;  
  reg CLK;  
  reg RST;  
  wire Q; 
  d_ff newD (.D(D), .clk(CLK), .rst(RST), .Q(Q)); 
 // clock  
  initial begin   
    CLK = 1'b0;  
    forever #5 CLK = ~CLK;  
  end  
// waveform dump  
  initial begin  
    $dumpfile("d_ff.vcd");   
    $dumpvars(0, TB_D);  
  end
  initial begin  
    RST = 1'b1; 
    D = 1'b0; #9;  
    RST = 1'b0; #6; 
    D = 1'b1; #7;    
    D = 1'b0; #9;    
    D = 1'b1; #11;  
    D = 1'b0; #6;    
    RST = 1'b1; #5;
    RST = 1'b0; #15;    
    $finish; 
  end
  initial begin   
    $monitor("Time=%0t | RST=%b | D=%b | Q=%b", $time, RST, D, Q);
  end
endmodule

sem3/DDCO_lab/week5/D_ff/d_ff.vcd
$date
	Wed Sep 17 07:12:15 2025
$end
$version
	Icarus Verilog
$end
$timescale
	1s
$end
$scope module TB_D $end
$var wire 1 ! Q $end
$var reg 1 " CLK $end
$var reg 1 # D $end
$var reg 1 $ RST $end
$scope module newD $end
$var wire 1 % D $end
$var wire 1 & clk $end
$var wire 1 ' rst $end
$var reg 1 ( Q $end
$upscope $end
$upscope $end
$enddefinitions $end
#0
$dumpvars
0(
1'
0&
0%
1$
0#
0"
0!
$end
#5
1"
1&
#9
0$
0'
#10
0"
0&
#15
1(
1!
1"
1&
1#
1%
#20
0"
0&
#22
0#
0%
#25
0(
0!
1"
1&
#30
0"
0&
#31
1#
1%
#35
1(
1!
1"
1&
#40
0"
0&
#42
0#
0%
#45
0(
0!
1"
1&
#48
1$
1'
#50
0"
0&
#53
0$
0'
